{"success":true,"cdma":false,"gsm":false,"lte":false,"nr":false,"wcdma":false,"wifi":true,"addresses":[],"results":[{"trilat":43.01948929,"trilong":-83.69882965,"ssid":"HOME-993B","qos":0,"transid":"20250308-02145","firsttime":"2025-03-09T03:35:00.000Z","lasttime":"2025-03-09T08:41:30.000Z","lastupdt":"2025-03-09T20:51:55.000Z","netid":"8C:61:A3:65:6F:B7","name":null,"type":"infra","comment":null,"wep":"2","bcninterval":0,"freenet":"?","dhcp":"?","paynet":"?","userfound":null,"channel":36,"frequency":5180,"rcois":null,"locationData":[{"alt":194,"accuracy":3.79009,"lastupdt":"2025-03-09T08:00:00.000Z","latitude":43.01937866,"longitude":-83.69882965,"month":"202503","ssid":"HOME-993B","time":"2025-03-08T08:00:00.000Z","signal":-63.0,"name":null,"netId":"154350981050295","noise":0.0,"snr":0.0,"wep":"2","channel":0,"frequency":5180,"encryptionValue":"WPA2"},{"alt":194,"accuracy":3.79009,"lastupdt":"2025-03-09T08:00:00.000Z","latitude":43.01935196,"longitude":-83.69924164,"month":"202503","ssid":"HOME-993B","time":"2025-03-08T08:00:00.000Z","signal":-70.0,"name":null,"netId":"154350981050295","noise":0.0,"snr":0.0,"wep":"2","channel":0,"frequency":5180,"encryptionValue":"WPA2"},{"alt":194,"accuracy":3.79009,"lastupdt":"2025-03-09T08:00:00.000Z","latitude":43.01942444,"longitude":-83.69907379,"month":"202503","ssid":"HOME-993B","time":"2025-03-08T08:00:00.000Z","signal":-75.0,"name":null,"netId":"154350981050295","noise":0.0,"snr":0.0,"wep":"2","channel":0,"frequency":5180,"encryptionValue":"WPA2"},{"alt":194,"accuracy":3.79009,"lastupdt":"2025-03-09T08:00:00.000Z","latitude":43.01944733,"longitude":-83.69902802,"month":"202503","ssid":"HOME-993B","time":"2025-03-08T08:00:00.000Z","signal":-82.0,"name":null,"netId":"154350981050295","noise":0.0,"snr":0.0,"wep":"2","channel":0,"frequency":5180,"encryptionValue":"WPA2"},{"alt":194,"accuracy":3.79009,"lastupdt":"2025-03-09T08:00:00.000Z","latitude":43.01949310,"longitude":-83.69892120,"month":"202503","ssid":"HOME-993B","time":"2025-03-08T08:00:00.000Z","signal":-87.0,"name":null,"netId":"154350981050295","noise":0.0,"snr":0.0,"wep":"2","channel":0,"frequency":5180,"encryptionValue":"WPA2"},{"alt":196,"accuracy":3.79009,"lastupdt":"2025-03-09T08:00:00.000Z","latitude":43.01984024,"longitude":-83.69781494,"month":"202503","ssid":"HOME-993B","time":"2025-03-08T08:00:00.000Z","signal":-91.0,"name":null,"netId":"154350981050295","noise":0.0,"snr":0.0,"wep":"2","channel":0,"frequency":5180,"encryptionValue":"WPA2"},{"alt":192,"accuracy":3.79009,"lastupdt":"2025-03-09T08:00:00.000Z","latitude":43.01965332,"longitude":-83.69857025,"month":"202503","ssid":"HOME-993B","time":"2025-03-08T08:00:00.000Z","signal":-92.0,"name":null,"netId":"154350981050295","noise":0.0,"snr":0.0,"wep":"2","channel":0,"frequency":5180,"encryptionValue":"WPA2"}],"encryption":"wpa2","country":"US","region":"MI","road":"University Avenue","city":"Flint","housenumber":null,"postalcode":"48503"}]}